mediapart_parser/__init__.py
mediapart_parser/mediapart_constants.py
mediapart_parser/mediapart_parser.py
mediapart_parser/test_mediapart_parser.py
mediapart_parser-1.0.9.dist-info/LICENSE
mediapart_parser-1.0.9.dist-info/METADATA
mediapart_parser-1.0.9.dist-info/WHEEL
mediapart_parser-1.0.9.dist-info/top_level.txt
mediapart_parser-1.0.9.dist-info/RECORD
