Metadata-Version: 2.1
Name: mediapart-parser
Version: 1.0.9
Summary: Provide tools to parse and download                 Mediapart articles as PDF.
Home-page: https://github.com/r0perice/mediapart-parser
Author: Robin Perice
Author-email: perice.robin@icloud.com
License: MIT
Download-URL: https://github.com/r0perice/    mediapart-parser/archive/1.0.9.tar.gz
Platform: UNKNOWN
License-File: LICENSE
Requires-Dist: feedparser
Requires-Dist: beautifulsoup4
Requires-Dist: requests
Requires-Dist: Deprecated
Requires-Dist: pdfkit
